{
  "style": {
    "showNow": true,
    "weekBarColor": "#EEEFF1",
    "weekBarTextColor": "#666",
    "taskTextColor": "#000303",
    "categories": {
      "deadlines": "#61CFED",
      "goals": "#5CCE99",
      "other": "#7D9CF9"
    }
  },
  "tasks": [
    {"name":"Initiation","type":"category","start":"2020-01-21","end":"2020-01-30"},
    {"name":"Project Introduction","type":"task","category":"other","start":"2020-01-21","end":"2020-01-24"},
    {"name":"Contract","type":"task","category":"deadlines","start":"2020-01-24","end":"2020-01-30"},

    {"name":"Planning","type":"category","start":"2020-01-30","end":"2020-03-14"},
    {"name":"Determine model","type":"task","category":"goals","start":"2020-01-30","end":"2020-03-14"},
    {"name":"Project Plan","type":"task","category":"deadlines","start":"2020-02-03","end":"2020-02-12"},

    {"name":"Execution","type":"category","start":"2020-02-12","end":"2020-05-14"},
    {"name":"Gather datasets","type":"task","category":"goals","start":"2020-02-12","end":"2020-02-20"},
    {"name":"Oral halftime presentation","type":"task","category":"deadlines","start":"2020-02-12","end":"2020-03-03"},
    {"name":"Dataset preprocessing","type":"task","category":"goals","start":"2020-03-03","end":"2020-03-14"},
    {"name":"Individual evaluation 1","type":"task","category":"deadlines","start":"2020-03-03","end":"2020-03-06"},
    {"name":"Final report pre-review","type":"task","category":"deadlines","start":"2020-03-06","end":"2020-04-29"},
    {"name":"Training","type":"task","category":"goals","start":"2020-03-14","end":"2020-04-24"},
    {"name":"Compiled final report","type":"task","category":"deadlines","start":"2020-04-29","end":"2020-05-14"},

    {"name":"Closure","type":"category","start":"2020-04-10","end":"2020-06-05"},
    {"name":"Evaluation","type":"task","category":"goals","start":"2020-04-10","end":"2020-05-10"},
    {"name":"Final presentation","type":"task","category":"deadlines","start":"2020-05-08","end":"2020-05-26"},
    {"name":"Exhibition","type":"task","category":"deadlines","start":"2020-05-12","end":"2020-05-19"},
    {"name":"Individual opposition","type":"task","category":"deadlines","start":"2020-05-14","end":"2020-05-20"},
    {"name":"Individual evaluation 2","type":"task","category":"deadlines","start":"2020-05-26","end":"2020-05-29"},
    {"name":"Final hand-in of report","type":"task","category":"deadlines","start":"2020-05-26","end":"2020-06-05"}
  ]
}

